AUTHORS
CHANGELOG.txt
DESCRIPTION
LICENSE
MANIFEST.in
README.rst
setup.py
django_homegate/__init__.py
django_homegate/admin.py
django_homegate/models.py
django_homegate/urls.py
django_homegate/views.py
django_homegate.egg-info/PKG-INFO
django_homegate.egg-info/SOURCES.txt
django_homegate.egg-info/dependency_links.txt
django_homegate.egg-info/requires.txt
django_homegate.egg-info/top_level.txt
django_homegate/management/__init__.py
django_homegate/management/commands/__init__.py
django_homegate/management/commands/push_to_homegate.py
django_homegate/static/.empty
django_homegate/templates/package_name/.empty
django_homegate/templatetags/__init__.py
django_homegate/templatetags/package_name_tags.py
django_homegate/tests/__init__.py
django_homegate/tests/factories.py
django_homegate/tests/models_tests.py
django_homegate/tests/runtests.py
django_homegate/tests/south_settings.py
django_homegate/tests/test_settings.py
django_homegate/tests/urls.py
django_homegate/tests/test_app/__init__.py
django_homegate/tests/test_app/models.py
django_homegate/tests/test_app/templates/400.html
django_homegate/tests/test_app/templates/500.html