Metadata-Version: 1.0
Name: django-homegate
Version: 0.1.1
Summary: django-homegate provides IDX3.01 API support for your Django project by closing the gap between python-homegate (https://github.com/arteria/python-homegate) and your real estate Django app.
